LICENSE
MANIFEST.in
README.md
setup.py
ntchat2/__init__.py
ntchat2.egg-info/PKG-INFO
ntchat2.egg-info/SOURCES.txt
ntchat2.egg-info/dependency_links.txt
ntchat2.egg-info/requires.txt
ntchat2.egg-info/top_level.txt
ntchat2/conf/__init__.py
ntchat2/const/__init__.py
ntchat2/const/notify_type.py
ntchat2/const/send_type.py
ntchat2/core/__init__.py
ntchat2/core/mgr.py
ntchat2/core/wechat.py
ntchat2/exception/__init__.py
ntchat2/utils/__init__.py
ntchat2/utils/logger.py
ntchat2/utils/singleton.py
ntchat2/utils/xdg.py
ntchat2/wc/__init__.py
ntchat2/wc/faker.exe
ntchat2/wc/helper_3.6.0.18.dat
ntchat2/wc/wcprobe.cp310-win32.pyd
ntchat2/wc/wcprobe.cp310-win_amd64.pyd
ntchat2/wc/wcprobe.cp311-win32.pyd
ntchat2/wc/wcprobe.cp311-win_amd64.pyd
ntchat2/wc/wcprobe.cp36-win32.pyd
ntchat2/wc/wcprobe.cp36-win_amd64.pyd
ntchat2/wc/wcprobe.cp37-win32.pyd
ntchat2/wc/wcprobe.cp37-win_amd64.pyd
ntchat2/wc/wcprobe.cp38-win32.pyd
ntchat2/wc/wcprobe.cp38-win_amd64.pyd
ntchat2/wc/wcprobe.cp39-win32.pyd
ntchat2/wc/wcprobe.cp39-win_amd64.pyd